{"cameraMode":{"drawMode":0,"name":"Shaded","section":"Shading Mode"},"sceneLighting":true,"audioPlay":false,"sceneViewState":{"m_AlwaysRefresh":false,"showFog":true,"showSkybox":true,"showFlares":true,"showImageEffects":true,"showParticleSystems":true,"showVisualEffectGraphs":true,"m_FxEnabled":true},"in2DMode":false,"pivot":{"x":4.072417259216309,"y":3.1272168159484865,"z":20.352718353271486},"rotation":{"x":-0.2892853319644928,"y":-0.07114646583795548,"z":0.021546313539147378,"w":-0.9543748497962952},"size":3.1686899662017824,"orthographic":false}